src/.DS_Store
src/data_pipeline/__init__.py
src/data_pipeline/feature_engineering/__init__.py
src/data_pipeline/feature_engineering/key_smash.py
src/data_pipeline/feature_engineering/word_embedding.py
src/data_pipeline/pre_processing/__init__.py
src/data_pipeline/pre_processing/concatenate_columns.py
src/main.py
src/parser/YAML_parser.py
src/parser/__init__.py
src/parser/const.py
src/parser/feature_engineering_parser.py
src/parser/model_parser.py
src/parser/parser_base.py
src/yamls/basic_example.yaml
trabalho_gces_eurico-7.4.dist-info/LICENSE
trabalho_gces_eurico-7.4.dist-info/WHEEL
trabalho_gces_eurico-7.4.dist-info/METADATA
trabalho_gces_eurico-7.4.dist-info/RECORD
