Metadata-Version: 2.1
Name: trabalho-gces-eurico
Version: 7.4
Summary: trabalho-gces-eurico-2023
Author: EuricoAbreu
Author-email: euricoabreuneto@hotmail.com
Requires-Python: >=3.8,<4.0
Classifier: Programming Language :: Python :: 3
Classifier: Programming Language :: Python :: 3.8
Classifier: Programming Language :: Python :: 3.9
Classifier: Programming Language :: Python :: 3.10
Classifier: Programming Language :: Python :: 3.11
